setup.py
irccat3/__init__.py
irccat3/bot.py
irccat3/listener.py
irccat3/main.py
irccat3.egg-info/PKG-INFO
irccat3.egg-info/SOURCES.txt
irccat3.egg-info/dependency_links.txt
irccat3.egg-info/entry_points.txt
irccat3.egg-info/requires.txt
irccat3.egg-info/top_level.txt
irccat3/tests/__init__.py
irccat3/tests/test_bot.py
irccat3/tests/test_listener.py
irccat3/tests/test_main.py