Metadata-Version: 1.0
Name: irccat3
Version: 0.1
Summary: IRCCat in Python
Home-page: https://github.com/jd-boyd/irccat3
Author: Joshua D. Boyd
Author-email: jdboyd@jdboyd.net
License: UNKNOWN
Platform: UNKNOWN
